MANIFEST.in
README.rst
setup.py
hiera/__init__.py
hiera/client.py
hiera/exc.py
hiera_py.egg-info/PKG-INFO
hiera_py.egg-info/SOURCES.txt
hiera_py.egg-info/dependency_links.txt
hiera_py.egg-info/top_level.txt