Metadata-Version: 1.1
Name: hiera-py
Version: 0.0.1
Summary: Python interface for the hiera hierachical database.
Home-page: http://thomasvandoren.github.com/hiera-py
Author: Thomas Van Doren
Author-email: thomas@thomasvandoren.com
License: BSD
Keywords: hiera
Platform: UNKNOWN
Classifier: Development Status :: 4 - Beta
Classifier: Intended Audience :: Developers
Classifier: License :: OSI Approved :: BSD License
Classifier: Operating System :: OS Independent
Classifier: Programming Language :: Python
Classifier: Programming Language :: Python :: 2.7
